{
  "version": "7",
  "dialect": "postgresql",
  "entries": [
    {
      "idx": 0,
      "version": "7",
      "when": 1718923027192,
      "tag": "0000_unique_colonel_america",
      "breakpoints": true
    },
    {
      "idx": 1,
      "version": "7",
      "when": 1718923639162,
      "tag": "0001_magenta_kitty_pryde",
      "breakpoints": true
    },
    {
      "idx": 2,
      "version": "7",
      "when": 1719060121687,
      "tag": "0002_busy_scorpion",
      "breakpoints": true
    },
    {
      "idx": 3,
      "version": "7",
      "when": 1720210895757,
      "tag": "0003_soft_young_avengers",
      "breakpoints": true
    }
  ]
}